Metadata-Version: 2.1
Name: pfcp
Version: 0.0.1
Summary: Track football game form terminal
Home-page: https://github.com/walidOumouzoune/PFC
Author: Walid OUMOUZOUNE
Author-email: walid.amozon@gmail.com
Project-URL: Bug Tracker, https://github.com/walidOumouzoune/FCP/issues
Classifier: Programming Language :: Python :: 3
Classifier: License :: OSI Approved :: MIT License
Classifier: Operating System :: OS Independent
Requires-Python: >=3.6
License-File: LICENSE
